<annotation>
  <folder/>
  <filename>0050.jpg</filename>
  <database/>
  <annotation/>
  <image/>
  <size>
    <height>500</height>
    <width>334</width>
    <depth>3</depth>
  </size>
  <segmented/>
  <object>
    <name>head</name>
    <pose/>
    <truncated/>
    <difficult/>
    <bndbox>
      <xmin>74.55223880597015</xmin>
      <ymin>61.19402985074627</ymin>
      <xmax>130.52238805970148</xmax>
      <ymax>122.38805970149254</ymax>
    </bndbox>
  </object>
  <object>
    <name>head</name>
    <pose/>
    <truncated/>
    <difficult/>
    <bndbox>
      <xmin>145.44776119402985</xmin>
      <ymin>54.4776119402985</ymin>
      <xmax>181.2686567164179</xmax>
      <ymax>99.25373134328358</ymax>
    </bndbox>
  </object>
  <object>
    <name>head</name>
    <pose/>
    <truncated/>
    <difficult/>
    <bndbox>
      <xmin>182.76119402985074</xmin>
      <ymin>48.50746268656716</ymin>
      <xmax>215.59701492537312</xmax>
      <ymax>90.29850746268656</ymax>
    </bndbox>
  </object>
  <object>
    <name>hand</name>
    <pose/>
    <truncated/>
    <difficult/>
    <bndbox>
      <xmin>223.8059701492537</xmin>
      <ymin>70.8955223880597</ymin>
      <xmax>261.1194029850746</xmax>
      <ymax>120.14925373134328</ymax>
    </bndbox>
  </object>
  <object>
    <name>hand</name>
    <pose/>
    <truncated/>
    <difficult/>
    <bndbox>
      <xmin>65.59701492537312</xmin>
      <ymin>153.73134328358208</ymin>
      <xmax>169.32835820895522</xmax>
      <ymax>197.0149253731343</ymax>
    </bndbox>
  </object>
  <object>
    <name>hand</name>
    <pose/>
    <truncated/>
    <difficult/>
    <bndbox>
      <xmin>162.61194029850745</xmin>
      <ymin>93.28358208955224</ymin>
      <xmax>188.73134328358208</xmax>
      <ymax>158.2089552238806</ymax>
    </bndbox>
  </object>
</annotation>
