<annotation>
  <folder/>
  <filename>0207.jpg</filename>
  <database/>
  <annotation/>
  <image/>
  <size>
    <height>480</height>
    <width>640</width>
    <depth>3</depth>
  </size>
  <segmented/>
  <object>
    <name>head</name>
    <pose/>
    <truncated/>
    <difficult/>
    <bndbox>
      <xmin>332.9896907216495</xmin>
      <ymin>271.2886597938144</ymin>
      <xmax>392.78350515463916</xmax>
      <ymax>340.36082474226805</ymax>
    </bndbox>
  </object>
  <object>
    <name>head</name>
    <pose/>
    <truncated/>
    <difficult/>
    <bndbox>
      <xmin>496.9072164948454</xmin>
      <ymin>162.01030927835052</ymin>
      <xmax>591.7525773195877</xmax>
      <ymax>267.16494845360825</ymax>
    </bndbox>
  </object>
  <object>
    <name>hand</name>
    <pose/>
    <truncated/>
    <difficult/>
    <bndbox>
      <xmin>294.8453608247423</xmin>
      <ymin>251.70103092783506</ymin>
      <xmax>332.9896907216495</xmax>
      <ymax>306.340206185567</ymax>
    </bndbox>
  </object>
  <object>
    <name>hand</name>
    <pose/>
    <truncated/>
    <difficult/>
    <bndbox>
      <xmin>308.2474226804124</xmin>
      <ymin>393.96907216494844</ymin>
      <xmax>387.62886597938143</xmax>
      <ymax>440.36082474226805</ymax>
    </bndbox>
  </object>
  <object>
    <name>hand</name>
    <pose/>
    <truncated/>
    <difficult/>
    <bndbox>
      <xmin>565.979381443299</xmin>
      <ymin>400.1546391752577</ymin>
      <xmax>639</xmax>
      <ymax>475</ymax>
    </bndbox>
  </object>
</annotation>
