<annotation>
  <folder/>
  <filename>0625.jpg</filename>
  <database/>
  <annotation/>
  <image/>
  <size>
    <height>480</height>
    <width>640</width>
    <depth>3</depth>
  </size>
  <segmented/>
  <object>
    <name>head</name>
    <pose/>
    <truncated/>
    <difficult/>
    <bndbox>
      <xmin>264.9484536082474</xmin>
      <ymin>73.35051546391753</ymin>
      <xmax>317.5257731958763</xmax>
      <ymax>130.0515463917526</ymax>
    </bndbox>
  </object>
  <object>
    <name>hand</name>
    <pose/>
    <truncated/>
    <difficult/>
    <bndbox>
      <xmin>160.82474226804123</xmin>
      <ymin>195.0</ymin>
      <xmax>195.87628865979383</xmax>
      <ymax>226.95876288659792</ymax>
    </bndbox>
  </object>
  <object>
    <name>hand</name>
    <pose/>
    <truncated/>
    <difficult/>
    <bndbox>
      <xmin>391.75257731958766</xmin>
      <ymin>189.84536082474227</ymin>
      <xmax>428.8659793814433</xmax>
      <ymax>234.17525773195877</ymax>
    </bndbox>
  </object>
</annotation>
