<annotation>
  <folder/>
  <filename>0675.jpg</filename>
  <database/>
  <annotation/>
  <image/>
  <size>
    <height>424</height>
    <width>640</width>
    <depth>3</depth>
  </size>
  <segmented/>
  <object>
    <name>head</name>
    <pose/>
    <truncated/>
    <difficult/>
    <bndbox>
      <xmin>203.09278350515464</xmin>
      <ymin>193.8041237113402</ymin>
      <xmax>252.57731958762886</xmax>
      <ymax>245.35051546391753</ymax>
    </bndbox>
  </object>
  <object>
    <name>head</name>
    <pose/>
    <truncated/>
    <difficult/>
    <bndbox>
      <xmin>306.1855670103093</xmin>
      <ymin>179.37113402061857</ymin>
      <xmax>353.60824742268045</xmax>
      <ymax>226.79381443298968</ymax>
    </bndbox>
  </object>
  <object>
    <name>head</name>
    <pose/>
    <truncated/>
    <difficult/>
    <bndbox>
      <xmin>457.7319587628866</xmin>
      <ymin>158.75257731958766</ymin>
      <xmax>514.4329896907217</xmax>
      <ymax>214.42268041237116</ymax>
    </bndbox>
  </object>
  <object>
    <name>hand</name>
    <pose/>
    <truncated/>
    <difficult/>
    <bndbox>
      <xmin>253.60824742268042</xmin>
      <ymin>330.9175257731959</ymin>
      <xmax>319.5876288659794</xmax>
      <ymax>371.1237113402062</ymax>
    </bndbox>
  </object>
  <object>
    <name>hand</name>
    <pose/>
    <truncated/>
    <difficult/>
    <bndbox>
      <xmin>318.55670103092785</xmin>
      <ymin>334.0103092783505</ymin>
      <xmax>352.5773195876289</xmax>
      <ymax>384.52577319587635</ymax>
    </bndbox>
  </object>
  <object>
    <name>hand</name>
    <pose/>
    <truncated/>
    <difficult/>
    <bndbox>
      <xmin>485.5670103092784</xmin>
      <ymin>307.2061855670103</ymin>
      <xmax>560.8247422680413</xmax>
      <ymax>350.50515463917526</ymax>
    </bndbox>
  </object>
</annotation>
